julius_tokenizer/__init__.py
julius_tokenizer/data/models/julius-base/tokenizer.json
julius_tokenizer/data/models/julius-base/tokenizer_config.json
julius_tokenizer/tokenizer/__init__.py
julius_tokenizer/tokenizer/processor.py
julius_tokenizer/tokenizer/tokenizer.py
julius_tokenizer/tokenizer/vocabulary.py
julius_nlp_tokenizer-0.1.0.dist-info/LICENSE
julius_nlp_tokenizer-0.1.0.dist-info/METADATA
julius_nlp_tokenizer-0.1.0.dist-info/WHEEL
julius_nlp_tokenizer-0.1.0.dist-info/top_level.txt
julius_nlp_tokenizer-0.1.0.dist-info/RECORD
