Metadata-Version: 2.2
Name: julius-nlp-tokenizer
Version: 0.1.0
Summary: A production-grade tokenizer for LLMs with perfect roundtrip accuracy
Home-page: https://github.com/username/julius_tokenizer
Author: Julius Tokenizer Team
Author-email: contact@novaintelligence.tech
Classifier: Programming Language :: Python :: 3
Classifier: Programming Language :: Python :: 3.8
Classifier: Programming Language :: Python :: 3.9
Classifier: Programming Language :: Python :: 3.10
Classifier: License :: OSI Approved :: MIT License
Classifier: Operating System :: OS Independent
Classifier: Topic :: Scientific/Engineering :: Artificial Intelligence
Classifier: Intended Audience :: Developers
Classifier: Intended Audience :: Science/Research
Classifier: Development Status :: 4 - Beta
Requires-Python: >=3.8
License-File: LICENSE
Requires-Dist: numpy>=1.20.0
Requires-Dist: tokenizers>=0.13.0
Requires-Dist: huggingface-hub>=0.10.0
Requires-Dist: torch>=1.10.0
Dynamic: author
Dynamic: author-email
Dynamic: classifier
Dynamic: description
Dynamic: description-content-type
Dynamic: home-page
Dynamic: requires-dist
Dynamic: requires-python
Dynamic: summary
